<annotation>
	<folder>dataset</folder>
	<filename>victim__401.png</filename>
	<path>D:\dataset\victim__401.png</path>
	<source>
		<database>Unknown</database>
	</source>
	<size>
		<width>512</width>
		<height>288</height>
		<depth>3</depth>
	</size>
	<segmented>0</segmented>
	<object>
		<name>person</name>
		<pose>Unspecified</pose>
		<truncated>0</truncated>
		<difficult>0</difficult>
		<bndbox>
			<xmin>64</xmin>
			<ymin>194</ymin>
			<xmax>143</xmax>
			<ymax>260</ymax>
		</bndbox>
	</object>
	<object>
		<name>person</name>
		<pose>Unspecified</pose>
		<truncated>1</truncated>
		<difficult>0</difficult>
		<bndbox>
			<xmin>1</xmin>
			<ymin>24</ymin>
			<xmax>104</xmax>
			<ymax>94</ymax>
		</bndbox>
	</object>
	<object>
		<name>person</name>
		<pose>Unspecified</pose>
		<truncated>1</truncated>
		<difficult>0</difficult>
		<bndbox>
			<xmin>452</xmin>
			<ymin>198</ymin>
			<xmax>512</xmax>
			<ymax>256</ymax>
		</bndbox>
	</object>
</annotation>
